dhg/__init__.py
dhg/_global.py
dhg/data/__init__.py
dhg/data/amazon.py
dhg/data/base.py
dhg/data/blogcatalog.py
dhg/data/citeseer.py
dhg/data/coauthorship.py
dhg/data/cocitation.py
dhg/data/cooking_200.py
dhg/data/cora.py
dhg/data/dblp.py
dhg/data/facebook.py
dhg/data/flickr.py
dhg/data/github.py
dhg/data/gowalla.py
dhg/data/imdb.py
dhg/data/movielens.py
dhg/data/news.py
dhg/data/pubmed.py
dhg/data/recipe.py
dhg/data/tencent.py
dhg/data/walmart.py
dhg/data/white_house.py
dhg/data/yelp.py
dhg/datapipe/__init__.py
dhg/datapipe/common.py
dhg/datapipe/loader.py
dhg/datapipe/normalize.py
dhg/experiments/__init__.py
dhg/experiments/base.py
dhg/experiments/recommender.py
dhg/experiments/vertex_classification.py
dhg/experiments/vertex_retrieval.py
dhg/experiments/graphs/__init__.py
dhg/experiments/graphs/graph.py
dhg/experiments/hypergraphs/__init__.py
dhg/experiments/hypergraphs/hypergraph.py
dhg/metrics/__init__.py
dhg/metrics/base.py
dhg/metrics/classification.py
dhg/metrics/link_prediction.py
dhg/metrics/recommender.py
dhg/metrics/retrieval.py
dhg/metrics/graphs/__init__.py
dhg/metrics/graphs/bipartite_graph.py
dhg/metrics/graphs/graph.py
dhg/metrics/hypergraphs/__init__.py
dhg/metrics/hypergraphs/hypergraph.py
dhg/models/__init__.py
dhg/models/graphs/__init__.py
dhg/models/graphs/bgnn.py
dhg/models/graphs/gat.py
dhg/models/graphs/gcn.py
dhg/models/graphs/gin.py
dhg/models/graphs/graphsage.py
dhg/models/graphs/lightgcn.py
dhg/models/graphs/ngcf.py
dhg/models/hypergraphs/__init__.py
dhg/models/hypergraphs/dhcf.py
dhg/models/hypergraphs/hgnn.py
dhg/models/hypergraphs/hgnnp.py
dhg/models/hypergraphs/hnhn.py
dhg/models/hypergraphs/hypergcn.py
dhg/models/hypergraphs/unignn.py
dhg/nn/__init__.py
dhg/nn/loss.py
dhg/nn/regularization.py
dhg/nn/convs/__init__.py
dhg/nn/convs/common.py
dhg/nn/convs/graphs/__init__.py
dhg/nn/convs/graphs/gat_conv.py
dhg/nn/convs/graphs/gcn_conv.py
dhg/nn/convs/graphs/gin_conv.py
dhg/nn/convs/graphs/graphsage_conv.py
dhg-0.9.5.dist-info/METADATA
dhg-0.9.5.dist-info/WHEEL
dhg-0.9.5.dist-info/licenses/LICENSE
dhg-0.9.5.dist-info/RECORD
