Metadata-Version: 2.4
Name: dhg
Version: 0.9.5
Summary: DHG is a Deep Learning Framework for Graph Neural Network and Hypergraph Neural Networks.
Author-email: yifanfeng97 <evanfeng97@qq.com>
License: Apache-2.0
License-File: LICENSE
Keywords: deep learning,graph neural networks,hypergraph neural networks,pytorch
Classifier: Development Status :: 4 - Beta
Classifier: Environment :: GPU :: NVIDIA CUDA
Classifier: Intended Audience :: Developers
Classifier: Intended Audience :: Education
Classifier: Intended Audience :: Science/Research
Classifier: License :: OSI Approved :: Apache Software License
Classifier: Operating System :: OS Independent
Classifier: Programming Language :: Python :: 3.8
Classifier: Programming Language :: Python :: 3.9
Classifier: Programming Language :: Python :: 3.10
Classifier: Programming Language :: Python :: 3.11
Classifier: Programming Language :: Python :: 3.12
Classifier: Topic :: Scientific/Engineering
Classifier: Topic :: Scientific/Engineering :: Artificial Intelligence
Classifier: Topic :: Scientific/Engineering :: Mathematics
Classifier: Topic :: Software Development
Classifier: Topic :: Software Development :: Libraries
Classifier: Topic :: Software Development :: Libraries :: Python Modules
Requires-Python: <3.13,>=3.8
Requires-Dist: matplotlib>=3.7.0
Requires-Dist: numpy<2.0
Requires-Dist: optuna
Requires-Dist: requests
Requires-Dist: scikit-learn
Requires-Dist: scipy>=1.8
Requires-Dist: torch<2.0,>=1.12.1
Provides-Extra: dev
Requires-Dist: black; extra == 'dev'
Requires-Dist: isort; extra == 'dev'
Requires-Dist: pytest; extra == 'dev'
